setup.py
django_rails_model.egg-info/PKG-INFO
django_rails_model.egg-info/SOURCES.txt
django_rails_model.egg-info/dependency_links.txt
django_rails_model.egg-info/requires.txt
django_rails_model.egg-info/top_level.txt
rails_model/__init__.py
rails_model/models.py