Metadata-Version: 1.0
Name: django-rails-model
Version: 0.1
Summary: Rails like models: hooks, first, last selectors, etc
Home-page: https://github.com/teodor-pripoae/django-rails-model
Author: Teodor Pripoae
Author-email: toni@netbaiji.com
License: UNKNOWN
Platform: UNKNOWN
